marytts_cli/__init__.py
marytts_cli/arguments.py
marytts_cli/client.py
marytts_cli/defaults.py
marytts_cli/response.py
marytts_cli-0.0.data/data/share/man/man1/marytts-cli.1
tests/__init__.py
tests/test_arguments.py
tests/test_client.py
marytts_cli-0.0.dist-info/LICENSE
marytts_cli-0.0.dist-info/METADATA
marytts_cli-0.0.dist-info/WHEEL
marytts_cli-0.0.dist-info/top_level.txt
marytts_cli-0.0.dist-info/RECORD
