Metadata-Version: 2.1
Name: marytts-cli
Version: 0.0
Summary: A command-line client for the HTTP server of the MaryTTS Text-To-Speech System.
Home-page: https://github.com/x3a/marytts-cli
Author: trevor
Author-email: trevor@destroyed.today
License: UNKNOWN
Keywords: marytts tts text-to-speech synthesis
Platform: UNKNOWN
Classifier: Development Status :: 3 - Alpha
Classifier: License :: OSI Approved :: MIT License
Classifier: Programming Language :: Python :: 2
Classifier: Programming Language :: Python :: 2.7
Classifier: Programming Language :: Python :: 3
Classifier: Programming Language :: Python :: 3.5
Classifier: Programming Language :: Python :: 3.6
Classifier: Programming Language :: Python :: 3.7
Classifier: Programming Language :: Python :: 3.8
Requires-Python: >=3
Requires-Dist: requests (==2.23.0)
Provides-Extra: doc
Requires-Dist: pdoc3 ; extra == 'doc'
Requires-Dist: argparse-manpage ; extra == 'doc'
Provides-Extra: test
Requires-Dist: coverage ; extra == 'test'
